
[
  {
    "_id": "1",
    "week_number": 4,
    "year": 2025,
    "platform": "wechat",
    "content_type": "产品发布",
    "publish_date": "2025-01-25",
    "publish_time": 1729392000000,
    "title": "AI太极SOS RING产品发布会预告",
    "content": "我们即将发布革命性的AI太极SOS RING智能戒指，融合主权AI技术与传统太极哲学，为您的健康生活保驾护航。产品采用先进的边缘计算架构，实现毫秒级响应和本地数据处理，确保您的隐私安全。敬请期待我们的正式发布会！",
    "script": "【开场】大家好，今天我们要为大家介绍一款革命性的智能穿戴产品。\n【产品介绍】AI太极SOS RING智能戒指，融合了传统太极哲学与现代AI技术。\n【核心功能】睡眠监测、SOS守护、健康追踪，全方位守护您的健康。\n【技术亮点】边缘计算、本地处理、隐私保护。\n【结尾】敬请期待我们的正式发布会，让我们一起开启智能健康新时代！",
    "resource_paths": [
      "/images/products/sos-ring-main.jpg",
      "/images/products/sos-ring-features.jpg",
      "/videos/product-teaser.mp4"
    ],
    "status": "scheduled",
    "priority": 1,
    "tags": ["产品发布", "智能戒指", "AI技术", "健康监测"],
    "target_audience": "科技爱好者、健康关注者、早期采用者",
    "content_purpose": "产品预热、品牌宣传、用户期待",
    "estimated_engagement": 5000,
    "actual_engagement": {
      "views": 0,
      "likes": 0,
      "shares": 0,
      "comments": 0,
      "clicks": 0
    },
    "publish_result": {},
    "error_message": "",
    "retry_count": 0,
    "auto_publish_enabled": true,
    "scheduled_publish": true,
    "approval_status": "approved",
    "approved_by": "marketing_manager",
    "approved_at": 1729391900000,
    "created_by": "content_creator_01",
    "assigned_to": "social_media_manager",
    "content_template_id": "template_product_launch",
    "campaign_id": "campaign_q1_2025",
    "seo_keywords": ["AI太极", "SOS戒指", "智能穿戴", "健康监测", "边缘计算"],
    "call_to_action": "点击了解更多产品详情",
    "content_length": 156,
    "reading_time": 2,
    "language": "zh-CN",
    "region": "中国大陆",
    "visibility": "public",
    "comments_enabled": true,
    "sharing_enabled": true,
    "analytics_tracked": true,
    "performance_metrics": {},
    "notes": "重点产品发布，需要多平台同步推广",
    "createdAt": 1729392000000,
    "updatedAt": 1729392000000
  },
  {
    "_id": "2",
    "week_number": 4,
    "year": 2025,
    "platform": "weibo",
    "content_type": "技术解析",
    "publish_date": "2025-01-24",
    "publish_time": 1729392300000,
    "title": "深度解析：AI太极的边缘计算架构",
    "content": "AI太极采用先进的边缘计算架构，实现毫秒级响应和本地数据处理。我们的技术团队经过多年研发，成功将复杂的AI算法部署到小型设备上，既保证了计算效率，又确保了用户隐私安全。这种架构设计让AI太极SOS RING能够在不依赖云端的情况下，实时处理健康数据并提供智能分析。",
    "script": "【技术背景】传统智能穿戴设备依赖云端计算，存在延迟和隐私风险。\n【解决方案】AI太极采用边缘计算架构，将AI算法部署到设备端。\n【技术优势】1. 毫秒级响应 2. 本地数据处理 3. 隐私保护 4. 低功耗设计\n【应用场景】睡眠分析、压力监测、健康预警等实时应用。\n【未来展望】持续优化算法性能，扩展更多应用场景。",
    "resource_paths": [
      "/images/tech/edge-computing-arch.jpg",
      "/images/tech/algorithm-flow.jpg",
      "/infographics/edge-vs-cloud.png"
    ],
    "status": "published",
    "priority": 2,
    "tags": ["技术解析", "边缘计算", "架构设计", "AI算法"],
    "target_audience": "技术从业者、开发者、科技爱好者",
    "content_purpose": "技术展示、专业形象建立、开发者吸引",
    "estimated_engagement": 3000,
    "actual_engagement": {
      "views": 1250,
      "likes": 89,
      "shares": 23,
      "comments": 15,
      "clicks": 45
    },
    "publish_result": {
      "platform_post_id": "WB_20250124_001",
      "publish_time": "2025-01-24T14:30:00Z",
      "success": true
    },
    "error_message": "",
    "retry_count": 0,
    "auto_publish_enabled": true,
    "scheduled_publish": true,
    "approval_status": "approved",
    "approved_by": "tech_lead",
    "approved_at": 1729392200000,
    "created_by": "tech_writer_01",
    "assigned_to": "tech_content_manager",
    "content_template_id": "template_tech_analysis",
    "campaign_id": "campaign_tech_2025",
    "seo_keywords": ["边缘计算", "AI架构", "智能穿戴", "算法优化", "隐私保护"],
    "call_to_action": "了解更多技术细节",
    "content_length": 198,
    "reading_time": 3,
    "language": "zh-CN",
    "region": "中国大陆",
    "visibility": "public",
    "comments_enabled": true,
    "sharing_enabled": true,
    "analytics_tracked": true,
    "performance_metrics": {
      "engagement_rate": 0.21,
      "click_through_rate": 0.036,
      "share_rate": 0.018
    },
    "notes": "技术深度内容，适合专业平台推广",
    "createdAt": 1729392100000,
    "updatedAt": 1729392300000
  },
  {
    "_id": "3",
    "week_number": 4,
    "year": 2025,
    "platform": "xiaohongshu",
    "content_type": "用户故事",
    "publish_date": "2025-01-23",
    "publish_time": 1729392600000,
    "title": "用户故事：AI太极如何改变我的睡眠质量",
    "content": "使用AI太极SOS RING三个月后，我的深睡时间提升了40%，整体睡眠质量显著改善。作为一个长期受失眠困扰的人，这款智能戒指真的改变了我的生活。它不仅能准确监测我的睡眠阶段，还能提供个性化的改善建议。现在我每天都能享受高质量的睡眠，白天的工作效率也大大提升了。",
    "script": "【用户背景】李女士，35岁，长期失眠患者，尝试过多种改善方法。\n【使用体验】使用AI太极SOS RING三个月的详细体验分享。\n【数据对比】使用前后的睡眠数据对比：深睡时间从45分钟提升到63分钟。\n【功能亮点】睡眠监测、个性化建议、长期趋势分析。\n【生活改变】睡眠质量改善带来的生活变化：工作效率提升、情绪改善。\n【推荐理由】真心推荐给有睡眠困扰的朋友，科技改变生活！",
    "resource_paths": [
      "/images/users/user-story-sleep.jpg",
      "/images/data/sleep-comparison.jpg",
      "/images/users/user-photo.jpg"
    ],
    "status": "draft",
    "priority": 3,
    "tags": ["用户故事", "睡眠改善", "产品体验", "真实案例"],
    "target_audience": "潜在用户、健康关注者、失眠人群",
    "content_purpose": "用户证言、产品效果展示、情感共鸣",
    "estimated_engagement": 4000,
    "actual_engagement": {
      "views": 0,
      "likes": 0,
      "shares": 0,
      "comments": 0,
      "clicks": 0
    },
    "publish_result": {},
    "error_message": "",
    "retry_count": 0,
    "auto_publish_enabled": true,
    "scheduled_publish": false,
    "approval_status": "pending",
    "approved_by": "",
    "approved_at": null,
    "created_by": "content_creator_02",
    "assigned_to": "community_manager",
    "content_template_id": "template_user_story",
    "campaign_id": "campaign_user_testimonials",
    "seo_keywords": ["睡眠改善", "用户体验", "智能戒指", "健康生活", "真实案例"],
    "call_to_action": "立即体验AI太极SOS RING",
    "content_length": 142,
    "reading_time": 2,
    "language": "zh-CN",
    "region": "中国大陆",
    "visibility": "public",
    "comments_enabled": true,
    "sharing_enabled": true,
    "analytics_tracked": true,
    "performance_metrics": {},
    "notes": "真实用户故事，需要用户授权和隐私保护",
    "createdAt": 1729392200000,
    "updatedAt": 1729392200000
  },
  {
    "_id": "4",
    "week_number": 3,
    "year": 2025,
    "platform": "zhihu",
    "content_type": "技术白皮书",
    "publish_date": "2025-01-22",
    "publish_time": 1729392900000,
    "title": "技术白皮书：主权AI时代的健康守护",
    "content": "详细解读AI太极SOS RING的技术架构、核心算法和创新应用场景。作为主权AI时代的代表性产品，AI太极SOS RING采用了多项创新技术，包括边缘计算、联邦学习、隐私保护等。本文将从技术架构、算法原理、应用场景等多个维度，全面解析这款产品的技术优势和创新点。",
    "script": "【引言】主权AI时代的到来及其对健康科技的影响。\n【技术架构】1. 硬件架构 2. 软件系统 3. AI算法栈\n【核心算法】1. 睡眠分析算法 2. 压力监测算法 3. 健康预测模型\n【创新应用】1. 实时健康监测 2. 个性化健康建议 3. 紧急救助系统\n【隐私保护】1. 本地数据处理 2. 联邦学习 3. 差分隐私\n【未来展望】技术演进路线图和应用前景。",
    "resource_paths": [
      "/documents/tech-whitepaper.pdf",
      "/images/tech/architecture-overview.jpg",
      "/charts/algorithm-performance.jpg"
    ],
    "status": "published",
    "priority": 2,
    "tags": ["技术白皮书", "主权AI", "健康守护", "深度解析"],
    "target_audience": "技术专家、研究者、行业分析师",
    "content_purpose": "技术权威展示、行业影响力建立、专业形象塑造",
    "estimated_engagement": 2500,
    "actual_engagement": {
      "views": 890,
      "likes": 67,
      "shares": 12,
      "comments": 8,
      "clicks": 34
    },
    "publish_result": {
      "platform_post_id": "ZH_20250122_001",
      "publish_time": "2025-01-22T09:00:00Z",
      "success": true
    },
    "error_message": "",
    "retry_count": 0,
    "auto_publish_enabled": true,
    "scheduled_publish": true,
    "approval_status": "approved",
    "approved_by": "cto",
    "approved_at": 1729392800000,
    "created_by": "tech_writer_02",
    "assigned_to": "tech_content_manager",
    "content_template_id": "template_whitepaper",
    "campaign_id": "campaign_thought_leadership",
    "seo_keywords": ["主权AI", "技术白皮书", "健康科技", "算法研究", "隐私保护"],
    "call_to_action": "下载完整技术白皮书",
    "content_length": 267,
    "reading_time": 4,
    "language": "zh-CN",
    "region": "中国大陆",
    "visibility": "public",
    "comments_enabled": true,
    "sharing_enabled": true,
    "analytics_tracked": true,
    "performance_metrics": {
      "engagement_rate": 0.11,
      "click_through_rate": 0.038,
      "share_rate": 0.013
    },
    "notes": "权威技术内容，适合知乎等专业平台",
    "createdAt": 1729392300000,
    "updatedAt": 1729392900000
  },
  {
    "_id": "5",
    "week_number": 3,
    "year": 2025,
    "platform": "linkedin",
    "content_type": "商业合作",
    "publish_date": "2025-01-21",
    "publish_time": 1729393200000,
    "title": "合作伙伴计划：携手共建AI生态",
    "content": "AI太极诚邀全球合作伙伴，共同打造主权AI时代的健康生态系统。我们提供开放的技术平台、完善的API接口、丰富的合作模式，期待与各行业的优秀企业携手，为全球用户提供更优质的健康服务。合作领域包括：硬件制造、软件开发、内容服务、渠道分销等。",
    "script": "【公司介绍】AI太极的使命和愿景。\n【市场机遇】主权AI时代的健康科技市场前景。\n【合作优势】1. 技术领先 2. 产品创新 3. 市场潜力 4. 支持体系\n【合作模式】1. 技术授权 2. 产品定制 3. 渠道合作 4. 内容合作\n【成功案例】现有合作伙伴的成功经验分享。\n【联系方式】商务合作联系方式和流程。",
    "resource_paths": [
      "/images/business/partner-program.jpg",
      "/documents/partner-prospectus.pdf",
      "/infographics/cooperation-models.jpg"
    ],
    "status": "failed",
    "priority": 2,
    "tags": ["合作伙伴", "生态建设", "商业合作", "B2B"],
    "target_audience": "企业决策者、商务拓展、投资者",
    "content_purpose": "商业拓展、合作伙伴招募、生态建设",
    "estimated_engagement": 1500,
    "actual_engagement": {
      "views": 0,
      "likes": 0,
      "shares": 0,
      "comments": 0,
      "clicks": 0
    },
    "publish_result": {},
    "error_message": "API连接超时，发布失败",
    "retry_count": 2,
    "auto_publish_enabled": true,
    "scheduled_publish": true,
    "approval_status": "approved",
    "approved_by": "business_director",
    "approved_at": 1729393100000,
    "created_by": "business_writer_01",
    "assigned_to": "business_development_manager",
    "content_template_id": "template_partnership",
    "campaign_id": "campaign_business_expansion",
    "seo_keywords": ["合作伙伴", "商业合作", "AI生态", "B2B", "技术授权"],
    "call_to_action": "立即申请成为合作伙伴",
    "content_length": 178,
    "reading_time": 2,
    "language": "zh-CN",
    "region": "全球",
    "visibility": "public",
    "comments_enabled": true,
    "sharing_enabled": true,
    "analytics_tracked": true,
    "performance_metrics": {},
    "notes": "重要商业内容，需要重新发布",
    "createdAt": 1729392400000,
    "updatedAt": 1729393200000
  },
  {
    "_id": "6",
    "week_number": 5,
    "year": 2025,
    "platform": "wechat",
    "content_type": "健康科普",
    "publish_date": "2025-01-28",
    "publish_time": 1729393500000,
    "title": "科学睡眠：如何通过数据改善睡眠质量",
    "content": "睡眠是人体最重要的生理过程之一，良好的睡眠质量对身心健康至关重要。AI太极SOS RING通过先进的传感器技术和AI算法，能够准确监测您的睡眠阶段，包括深睡、浅睡、REM睡眠等，并提供科学的改善建议。让我们一起了解如何通过数据驱动的方